psautohint/__init__.py
psautohint/__main__.py
psautohint/_psautohint.cpython-39-darwin.so
psautohint/autohint.py
psautohint/fdTools.py
psautohint/otfFont.py
psautohint/ufoFont.py
psautohint-2.4.0.dist-info/LICENSE
psautohint-2.4.0.dist-info/METADATA
psautohint-2.4.0.dist-info/WHEEL
psautohint-2.4.0.dist-info/entry_points.txt
psautohint-2.4.0.dist-info/top_level.txt
psautohint-2.4.0.dist-info/RECORD
