Metadata-Version: 2.1
Name: psautohint
Version: 2.4.0
Summary: Python wrapper for Adobe's PostScript autohinter
Home-page: https://github.com/adobe-type-tools/psautohint
Author: Adobe Type team & friends
Author-email: afdko@adobe.com
License: Apache License, Version 2.0
Platform: UNKNOWN
Classifier: Development Status :: 5 - Production/Stable
Classifier: Environment :: Console
Classifier: Intended Audience :: Developers
Classifier: License :: OSI Approved :: Apache Software License
Classifier: Natural Language :: English
Classifier: Operating System :: OS Independent
Classifier: Programming Language :: Python
Classifier: Programming Language :: Python :: 3 :: Only
Classifier: Programming Language :: Python :: 3.7
Classifier: Topic :: Text Processing :: Fonts
Classifier: Topic :: Multimedia :: Graphics
Classifier: Topic :: Multimedia :: Graphics :: Graphics Conversion
Requires-Python: >3.7
License-File: LICENSE
Requires-Dist: fonttools[ufo] (>=4.22.0)
Provides-Extra: testing
Requires-Dist: pytest (<4,>=3.0.0) ; extra == 'testing'
Requires-Dist: pytest-cov (<3,>=2.5.1) ; extra == 'testing'
Requires-Dist: pytest-xdist (<1.28.0,>=1.22.2) ; extra == 'testing'
Requires-Dist: pytest-randomly (<2,>=1.2.3) ; extra == 'testing'
